funai/__init__.py
funai/llm/__init__.py
funai/llm/base.py
funai/llm/models.py
funai-1.0.7.dist-info/METADATA
funai-1.0.7.dist-info/WHEEL
funai-1.0.7.dist-info/top_level.txt
funai-1.0.7.dist-info/RECORD
