Metadata-Version: 2.2
Name: funai
Version: 1.0.7
Summary: funai
Author-email: niuliangtao <farfarfun@qq.com>
Requires-Python: >=3.8
Requires-Dist: funsecret>=1.4.38
Requires-Dist: funutil>=1.0.46
